geofinder/AppLayout.py
geofinder/AppStyle.py
geofinder/GeoFinder.py
geofinder/GrampsCsv.py
geofinder/__init__.py
geofinder/__version__.py
geofinder/ancestry/AncestryFile.py
geofinder/ancestry/Gedcom.py
geofinder/ancestry/GrampsXml.py
geofinder/ancestry/__init__.py
geofinder/images/__init__.py
geofinder/images/exit.gif
geofinder/images/folder.gif
geofinder/images/help.gif
geofinder/images/map.gif
geofinder/images/play.gif
geofinder/images/save.gif
geofinder/images/search.gif
geofinder/images/skip.gif
geofinder/images/verify.gif
geofinder/test/Test.py
geofinder/test/TestCSV.py
geofinder/test/__init__.py
geofinder/util/ArgumentParserNoExitZZZ.py
geofinder/util/CachedDictionary.py
geofinder/util/Config.py
geofinder/util/FileReader.py
geofinder/util/GridPosition.py
geofinder/util/IniHandler.py
geofinder/util/SpellCheck.py
geofinder/util/Tooltip.py
geofinder/util/__init__.py
geofinder/util_menu/UtilCountriesFrame.py
geofinder/util_menu/UtilErrorFrame.py
geofinder/util_menu/UtilFeatureFrame.py
geofinder/util_menu/UtilLanguagesFrame.py
geofinder/util_menu/UtilLayout.py
geofinder/util_menu/UtilListboxFrame.py
geofinder/util_menu/UtilMain.py
geofinder/util_menu/UtilOutputFilterFrame.py
geofinder/util_menu/UtilReplaceFrame.py
geofinder/util_menu/__init__.py
geofinder-1.0.8.dist-info/LICENSE
geofinder-1.0.8.dist-info/METADATA
geofinder-1.0.8.dist-info/WHEEL
geofinder-1.0.8.dist-info/entry_points.txt
geofinder-1.0.8.dist-info/top_level.txt
geofinder-1.0.8.dist-info/RECORD
