Metadata-Version: 2.1
Name: geofinder
Version: 1.0.8
Summary: GEDCOM Genealogy address validation and geocoding using geonames.org data
Home-page: https://github.com/corb555/GeoFinder
Author: Mike Herbert
Author-email: corb@aol.com
License: MIT
Platform: UNKNOWN
Classifier: Programming Language :: Python :: 3.6
Classifier: License :: OSI Approved :: BSD License
Classifier: Operating System :: OS Independent
Classifier: Development Status :: 4 - Beta
Classifier: Intended Audience :: End Users/Desktop
Classifier: Natural Language :: English
Classifier: Topic :: Sociology :: Genealogy
Requires-Dist: tk-helper
Requires-Dist: geodata
